{
  "servicechain": {
    "SC1": {
      "resptime": 15.161791384315615,
      "resptime_old": 5.161791384315616,
      "waittime": 2.946176779158766,
      "servicetime": 10.0,
      "networktime": 2.215614605156849,
      "services": {
        "MS1_1": {
          "meanserv": 1.294879126213948,
          "stddevserv": 1.294879126213948,
          "rate": 0.7722728552462385,
          "cv": 1.0,
          "lambda": 0.05
        },
        "MS1_2": {
          "meanserv": 4.522110075630792,
          "stddevserv": 4.522110075630792,
          "rate": 0.22113570507469554,
          "cv": 1.0,
          "lambda": 0.05
        },
        "MS1_3": {
          "meanserv": 2.6060131903547656,
          "stddevserv": 2.6060131903547656,
          "rate": 0.38372791193120037,
          "cv": 1.0,
          "lambda": 0.05
        },
        "MS1_4": {
          "meanserv": 0.9617174588788533,
          "stddevserv": 0.9617174588788533,
          "rate": 1.0398064325106207,
          "cv": 1.0,
          "lambda": 0.05
        },
        "MS1_5": {
          "meanserv": 0.6152801489216415,
          "stddevserv": 0.6152801489216415,
          "rate": 1.6252759035906328,
          "cv": 1.0,
          "lambda": 0.05
        }
      },
      "sensors": [
        "S1"
      ],
      "sources": [
        {
          "startTime": 0,
          "stopTime": -1,
          "lambda": 0.05
        }
      ]
    },
    "SC2": {
      "resptime": 15.30781795428959,
      "resptime_old": 5.3078179542895905,
      "waittime": 3.712534903263536,
      "servicetime": 10.0,
      "networktime": 1.5952830510260538,
      "services": {
        "MS2_1": {
          "meanserv": 5.657926975137305,
          "stddevserv": 5.657926975137305,
          "rate": 0.17674317897602987,
          "cv": 1.0,
          "lambda": 0.05
        },
        "MS2_2": {
          "meanserv": 0.6007711458668066,
          "stddevserv": 0.6007711458668066,
          "rate": 1.664527344363679,
          "cv": 1.0,
          "lambda": 0.05
        },
        "MS2_3": {
          "meanserv": 0.5980459182359139,
          "stddevserv": 0.5980459182359139,
          "rate": 1.672112407270917,
          "cv": 1.0,
          "lambda": 0.05
        },
        "MS2_4": {
          "meanserv": 1.3101506288150553,
          "stddevserv": 1.3101506288150553,
          "rate": 0.7632710148026521,
          "cv": 1.0,
          "lambda": 0.05
        },
        "MS2_5": {
          "meanserv": 1.8331053319449193,
          "stddevserv": 1.8331053319449193,
          "rate": 0.5455223890156945,
          "cv": 1.0,
          "lambda": 0.05
        }
      },
      "sensors": [
        "S2"
      ],
      "sources": [
        {
          "startTime": 0,
          "stopTime": -1,
          "lambda": 0.05
        }
      ]
    },
    "SC3": {
      "resptime": 17.39664933841644,
      "resptime_old": 7.396649338416442,
      "waittime": 3.8188085936564935,
      "servicetime": 10.0,
      "networktime": 3.577840744759948,
      "services": {
        "MS3_1": {
          "meanserv": 1.0163289340828507,
          "stddevserv": 1.0163289340828507,
          "rate": 0.9839334161064831,
          "cv": 1.0,
          "lambda": 0.05
        },
        "MS3_2": {
          "meanserv": 4.388633950164985,
          "stddevserv": 4.388633950164985,
          "rate": 0.22786133711662288,
          "cv": 1.0,
          "lambda": 0.05
        },
        "MS3_3": {
          "meanserv": 0.2598947338637956,
          "stddevserv": 0.2598947338637956,
          "rate": 3.8477116682328596,
          "cv": 1.0,
          "lambda": 0.05
        },
        "MS3_4": {
          "meanserv": 0.2962585156772821,
          "stddevserv": 0.2962585156772821,
          "rate": 3.3754303997435526,
          "cv": 1.0,
          "lambda": 0.05
        },
        "MS3_5": {
          "meanserv": 4.038883866211086,
          "stddevserv": 4.038883866211086,
          "rate": 0.24759315521941688,
          "cv": 1.0,
          "lambda": 0.05
        }
      },
      "sensors": [
        "S3"
      ],
      "sources": [
        {
          "startTime": 0,
          "stopTime": -1,
          "lambda": 0.05
        }
      ]
    },
    "SC4": {
      "resptime": 16.304475374592904,
      "resptime_old": 6.3044753745929025,
      "waittime": 4.408609228646849,
      "servicetime": 10.0,
      "networktime": 1.895866145946054,
      "services": {
        "MS4_1": {
          "meanserv": 0.4086000629227937,
          "stddevserv": 0.4086000629227937,
          "rate": 2.4473809251198113,
          "cv": 1.0,
          "lambda": 0.05
        },
        "MS4_2": {
          "meanserv": 0.7563684634237211,
          "stddevserv": 0.7563684634237211,
          "rate": 1.3221069470208666,
          "cv": 1.0,
          "lambda": 0.05
        },
        "MS4_3": {
          "meanserv": 2.064653026356833,
          "stddevserv": 2.064653026356833,
          "rate": 0.48434288339699477,
          "cv": 1.0,
          "lambda": 0.05
        },
        "MS4_4": {
          "meanserv": 2.982439825910113,
          "stddevserv": 2.982439825910113,
          "rate": 0.3352959517615222,
          "cv": 1.0,
          "lambda": 0.05
        },
        "MS4_5": {
          "meanserv": 3.787938621386539,
          "stddevserv": 3.787938621386539,
          "rate": 0.2639958299097147,
          "cv": 1.0,
          "lambda": 0.05
        }
      },
      "sensors": [
        "S4"
      ],
      "sources": [
        {
          "startTime": 0,
          "stopTime": -1,
          "lambda": 0.05
        }
      ]
    }
  },
  "microservice": {
    "MS1_1": "F10",
    "MS1_2": "F7",
    "MS1_3": "F9",
    "MS1_4": "F9",
    "MS1_5": "F9",
    "MS2_1": "F6",
    "MS2_2": "F2",
    "MS2_3": "F2",
    "MS2_4": "F2",
    "MS2_5": "F2",
    "MS3_1": "F3",
    "MS3_2": "F3",
    "MS3_3": "F1",
    "MS3_4": "F1",
    "MS3_5": "F5",
    "MS4_1": "F4",
    "MS4_2": "F4",
    "MS4_3": "F4",
    "MS4_4": "F8",
    "MS4_5": "F8"
  },
  "sensor": {
    "S1": "F10",
    "S2": "F6",
    "S3": "F3",
    "S4": "F4"
  },
  "fog": {
    "F1": {
      "rho": 0.027807662477053886,
      "capacity": 1.0,
      "tserv": 0.27807662477053885,
      "stddev": 0.27926290759365896,
      "mu": 3.596131105320961,
      "cv": 1.0042660285599303,
      "lambda": 0.1,
      "twait": 0.007987842261602571
    },
    "F2": {
      "rho": 0.21710365124313472,
      "capacity": 1.0,
      "tserv": 1.0855182562156735,
      "stddev": 1.3112312818605072,
      "mu": 0.9212189608733006,
      "cv": 1.2079311189401023,
      "lambda": 0.2,
      "twait": 0.3701227325568947
    },
    "F3": {
      "rho": 0.27024814421239185,
      "capacity": 1.0,
      "tserv": 2.7024814421239185,
      "stddev": 3.604112443552578,
      "mu": 0.3700302930532192,
      "cv": 1.3336307836845143,
      "lambda": 0.1,
      "twait": 1.3904063614125926
    },
    "F4": {
      "rho": 0.1614810776351674,
      "capacity": 1.0,
      "tserv": 1.0765405175677825,
      "stddev": 1.4749983399265771,
      "mu": 0.9289014056426694,
      "cv": 1.3701280312784014,
      "lambda": 0.15000000000000002,
      "twait": 0.29825441321112145
    },
    "F5": {
      "rho": 0.20194419331055433,
      "capacity": 1.0,
      "tserv": 4.038883866211086,
      "stddev": 4.038883866211086,
      "mu": 0.24759315521941688,
      "cv": 1.0,
      "lambda": 0.05,
      "twait": 1.0220201863081029
    },
    "F6": {
      "rho": 0.28289634875686526,
      "capacity": 1.0,
      "tserv": 5.657926975137305,
      "stddev": 5.657926975137305,
      "mu": 0.17674317897602987,
      "cv": 1.0,
      "lambda": 0.05,
      "twait": 2.232043973035958
    },
    "F7": {
      "rho": 0.22610550378153962,
      "capacity": 1.0,
      "tserv": 4.522110075630792,
      "stddev": 4.522110075630792,
      "mu": 0.22113570507469554,
      "cv": 1.0,
      "lambda": 0.05,
      "twait": 1.3212059031331387
    },
    "F8": {
      "rho": 0.3385189223648326,
      "capacity": 1.0,
      "tserv": 3.385189223648326,
      "stddev": 3.4327715092417304,
      "mu": 0.2954044615923326,
      "cv": 1.0140560194570523,
      "lambda": 0.1,
      "twait": 1.7569229945067422
    },
    "F9": {
      "rho": 0.20915053990776306,
      "capacity": 1.0,
      "tserv": 1.39433693271842,
      "stddev": 1.858047659553533,
      "mu": 0.7171867692340222,
      "cv": 1.332567198038035,
      "lambda": 0.15000000000000002,
      "twait": 0.5117772274718609
    },
    "F10": {
      "rho": 0.0647439563106974,
      "capacity": 1.0,
      "tserv": 1.294879126213948,
      "stddev": 1.294879126213948,
      "mu": 0.7722728552462385,
      "cv": 1.0,
      "lambda": 0.05,
      "twait": 0.08963919361004476
    }
  },
  "extra": {
    "conv_gen": 30,
    "max_gen": 600,
    "population": 600,
    "deltatime": 38.1967478,
    "obj_func": 16.042683512903636
  },
  "network": [
    [
      0.0,
      1.4655892795324192,
      1.8854079116122757,
      1.9967869938615017,
      1.6924328331476726,
      2.9169186398990536,
      1.8885509741321393,
      2.10424724363666,
      1.850945873053937,
      1.850945873053937
    ],
    [
      1.4655892795324192,
      0.0,
      2.3123452499998116,
      1.4928307575348256,
      2.474723113958528,
      1.5952830510260538,
      2.155699346686499,
      1.850945873053937,
      1.9202300989903778,
      1.9202300989903778
    ],
    [
      1.8854079116122757,
      2.3123452499998116,
      0.0,
      1.4800729840196,
      2.288983704248935,
      1.7474686064652847,
      2.10424724363666,
      1.9202300989903778,
      1.895866145946054,
      1.895866145946054
    ],
    [
      1.9967869938615017,
      1.4928307575348256,
      1.4800729840196,
      0.0,
      2.563242788344554,
      1.8885509741321393,
      1.850945873053937,
      1.895866145946054,
      3.1508625011564213,
      3.1508625011564213
    ],
    [
      1.6924328331476726,
      2.474723113958528,
      2.288983704248935,
      2.563242788344554,
      0.0,
      2.155699346686499,
      1.9202300989903778,
      3.1508625011564213,
      1.7667727741261903,
      1.7667727741261903
    ],
    [
      2.9169186398990536,
      1.5952830510260538,
      1.7474686064652847,
      1.8885509741321393,
      2.155699346686499,
      0.0,
      1.895866145946054,
      1.7667727741261903,
      1.8482381023173382,
      1.8482381023173382
    ],
    [
      1.8885509741321393,
      2.155699346686499,
      2.10424724363666,
      1.850945873053937,
      1.9202300989903778,
      1.895866145946054,
      0.0,
      1.8482381023173382,
      1.1078073025784245,
      1.1078073025784245
    ],
    [
      2.10424724363666,
      1.850945873053937,
      1.9202300989903778,
      1.895866145946054,
      3.1508625011564213,
      1.7667727741261903,
      1.8482381023173382,
      0.0,
      1.7059569440769227,
      1.7059569440769227
    ],
    [
      1.850945873053937,
      1.9202300989903778,
      1.895866145946054,
      3.1508625011564213,
      1.7667727741261903,
      1.8482381023173382,
      1.1078073025784245,
      1.7059569440769227,
      0.0,
      1.371064836112943
    ],
    [
      1.850945873053937,
      1.9202300989903778,
      1.895866145946054,
      3.1508625011564213,
      1.7667727741261903,
      1.8482381023173382,
      1.1078073025784245,
      1.7059569440769227,
      1.371064836112943,
      0.0
    ]
  ]
}